cos_aspera-0.1.163682.data/purelib/cos_aspera/__init__.py
cos_aspera-0.1.163682.data/purelib/cos_aspera/_faspmanager2.so
cos_aspera-0.1.163682.data/purelib/cos_aspera/ascp
cos_aspera-0.1.163682.data/purelib/cos_aspera/aspera-license
cos_aspera-0.1.163682.data/purelib/cos_aspera/aspera.conf
cos_aspera-0.1.163682.data/purelib/cos_aspera/aspera_tokenauth_id_rsa
cos_aspera-0.1.163682.data/purelib/cos_aspera/aspera_web_cert.pem
cos_aspera-0.1.163682.data/purelib/cos_aspera/aspera_web_key.pem
cos_aspera-0.1.163682.data/purelib/cos_aspera/asperaweb_id_dsa.openssh
cos_aspera-0.1.163682.data/purelib/cos_aspera/asperaweb_id_dsa.putty
cos_aspera-0.1.163682.data/purelib/cos_aspera/faspmanager2.py
cos_aspera-0.1.163682.data/purelib/cos_aspera/test.py
cos_aspera-0.1.163682.data/purelib/cos_aspera/transferspec.py
cos_aspera-0.1.163682.data/purelib/cos_aspera/pydocs/annotated.html
cos_aspera-0.1.163682.data/purelib/cos_aspera/pydocs/annotated_dup.js
cos_aspera-0.1.163682.data/purelib/cos_aspera/pydocs/bc_s.png
cos_aspera-0.1.163682.data/purelib/cos_aspera/pydocs/bdwn.png
cos_aspera-0.1.163682.data/purelib/cos_aspera/pydocs/classes.html
cos_aspera-0.1.163682.data/purelib/cos_aspera/pydocs/classfaspmanager2_1_1__object.html
cos_aspera-0.1.163682.data/purelib/cos_aspera/pydocs/classfaspmanager2_1_1__object.png
cos_aspera-0.1.163682.data/purelib/cos_aspera/pydocs/classfaspmanager2_1_1_i_transfer_listener-members.html
cos_aspera-0.1.163682.data/purelib/cos_aspera/pydocs/classfaspmanager2_1_1_i_transfer_listener.html
cos_aspera-0.1.163682.data/purelib/cos_aspera/pydocs/classfaspmanager2_1_1_i_transfer_listener.js
cos_aspera-0.1.163682.data/purelib/cos_aspera/pydocs/classfaspmanager2_1_1_i_transfer_listener.png
cos_aspera-0.1.163682.data/purelib/cos_aspera/pydocs/classtransferspec_1_1_node_error-members.html
cos_aspera-0.1.163682.data/purelib/cos_aspera/pydocs/classtransferspec_1_1_node_error.html
cos_aspera-0.1.163682.dist-info/METADATA
cos_aspera-0.1.163682.dist-info/RECORD
cos_aspera-0.1.163682.dist-info/WHEEL
cos_aspera-0.1.163682.dist-info/top_level.txt
