Metadata-Version: 2.1
Name: cos-aspera
Version: 0.1.163682
Summary: Interface to Aspera for ICOS
Home-page: https://asperasoft.com
Author: Aspera SWD
Author-email: aspera-release@ibm.com
License: UNKNOWN
Platform: UNKNOWN
Classifier: Programming Language :: Python :: 3.6
Classifier: License :: Other/Proprietary License
Classifier: Operating System :: MacOS :: MacOS X
